texsquisite/__init__.py
texsquisite/rules.py
texsquisite/run.py
texsquisite/utils.py
texsquisite-0.0.2.dist-info/LICENSE
texsquisite-0.0.2.dist-info/METADATA
texsquisite-0.0.2.dist-info/WHEEL
texsquisite-0.0.2.dist-info/entry_points.txt
texsquisite-0.0.2.dist-info/top_level.txt
texsquisite-0.0.2.dist-info/RECORD
