Metadata-Version: 2.2
Name: texsquisite
Version: 0.0.2
Summary: A LaTex linter written in Python
Author-email: Philip Mocz <philip.mocz@gmail.com>
License: MIT License
Project-URL: Documentation, https://texsquisite.readthedocs.io
Project-URL: Homepage, https://github.com/pmocz/texsquisite
Requires-Python: >=3.12
License-File: LICENSE
Requires-Dist: toml
